pacdb.py
pacdb-0.1.0.dist-info/LICENSE
pacdb-0.1.0.dist-info/WHEEL
pacdb-0.1.0.dist-info/METADATA
pacdb-0.1.0.dist-info/RECORD
